RsCMPX_WlanMeas/RsCMPX_WlanMeas.py
RsCMPX_WlanMeas/__init__.py
RsCMPX_WlanMeas/enums.py
RsCMPX_WlanMeas/repcap.py
RsCMPX_WlanMeas/CustomFiles/__init__.py
RsCMPX_WlanMeas/CustomFiles/events.py
RsCMPX_WlanMeas/CustomFiles/reliability.py
RsCMPX_WlanMeas/CustomFiles/utilities.py
RsCMPX_WlanMeas/Implementations/__init__.py
RsCMPX_WlanMeas/Implementations/Configure/__init__.py
RsCMPX_WlanMeas/Implementations/Configure/WlanMeas/Mimo.py
RsCMPX_WlanMeas/Implementations/Configure/WlanMeas/Smimo.py
RsCMPX_WlanMeas/Implementations/Configure/WlanMeas/__init__.py
RsCMPX_WlanMeas/Implementations/Configure/WlanMeas/Isignal/Ofdm.py
RsCMPX_WlanMeas/Implementations/Configure/WlanMeas/Isignal/__init__.py
RsCMPX_WlanMeas/Implementations/Configure/WlanMeas/Isignal/Dsss/Elength.py
RsCMPX_WlanMeas/Implementations/Configure/WlanMeas/Isignal/Dsss/__init__.py
RsCMPX_WlanMeas/Implementations/Configure/WlanMeas/Isignal/Tdata/File.py
RsCMPX_WlanMeas/Implementations/Configure/WlanMeas/Isignal/Tdata/__init__.py
RsCMPX_WlanMeas/Implementations/Configure/WlanMeas/MultiEval/PowerVsTime.py
RsCMPX_WlanMeas/Implementations/Configure/WlanMeas/MultiEval/Result.py
RsCMPX_WlanMeas/Implementations/Configure/WlanMeas/MultiEval/Scount.py
RsCMPX_WlanMeas/Implementations/Configure/WlanMeas/MultiEval/SpectrFlatness.py
RsCMPX_WlanMeas/Implementations/Configure/WlanMeas/MultiEval/TsMask.py
RsCMPX_WlanMeas/Implementations/Configure/WlanMeas/MultiEval/__init__.py
RsCMPX_WlanMeas/Implementations/Configure/WlanMeas/MultiEval/Compensation/EfTaps.py
RsCMPX_WlanMeas/Implementations/Configure/WlanMeas/MultiEval/Compensation/SkipSymbols.py
RsCMPX_WlanMeas/Implementations/Configure/WlanMeas/MultiEval/Compensation/Tracking.py
RsCMPX_WlanMeas/Implementations/Configure/WlanMeas/MultiEval/Compensation/__init__.py
RsCMPX_WlanMeas/Implementations/Configure/WlanMeas/MultiEval/Demod/Fft.py
RsCMPX_WlanMeas/Implementations/Configure/WlanMeas/MultiEval/Demod/__init__.py
RsCMPX_WlanMeas-5.0.80.dist-info/METADATA
RsCMPX_WlanMeas-5.0.80.dist-info/WHEEL
RsCMPX_WlanMeas-5.0.80.dist-info/top_level.txt
RsCMPX_WlanMeas-5.0.80.dist-info/RECORD
